librespeed/__init__.py
librespeed/constants.py
librespeed-1.0.0a1.dist-info/LICENSE
librespeed-1.0.0a1.dist-info/METADATA
librespeed-1.0.0a1.dist-info/WHEEL
librespeed-1.0.0a1.dist-info/top_level.txt
librespeed-1.0.0a1.dist-info/RECORD
