Metadata-Version: 2.1
Name: librespeed
Version: 1.0.0a1
Summary: A Python client library for LibreSpeed
Home-page: https://github.com/dopstar/librespeed
Author: Mkhanyisi Madlavana
Author-email: mmadlavana@gmail.com
License: MIT
Download-URL: https://github.com/dopstar/librespeed/archive/1.0.0a1.tar.gz
Project-URL: Documentation, https://dopstar.github.io/librespeed
Project-URL: Source, https://github.com/dopstar/librespeed
Project-URL: Tracker, https://github.com/dopstar/librespeed/issues
Keywords: LibreSpeed,speedtest
Platform: UNKNOWN
Classifier: Development Status :: 3 - Alpha
Classifier: Intended Audience :: Developers
Classifier: Natural Language :: English
Classifier: Programming Language :: Python
Classifier: Programming Language :: Python :: 3.6
Classifier: Programming Language :: Python :: 3.7
Classifier: Programming Language :: Python :: 3.8
Classifier: Programming Language :: Python :: 3.9
Classifier: License :: OSI Approved :: MIT License
Classifier: Operating System :: MacOS
Classifier: Operating System :: POSIX :: Linux
Classifier: Operating System :: Microsoft :: Windows
Classifier: Topic :: Software Development :: Version Control :: Git
Classifier: Programming Language :: Python :: Implementation :: CPython
License-File: LICENSE
Requires-Dist: requests
Provides-Extra: linting
Requires-Dist: flake8 ; extra == 'linting'
Requires-Dist: banditflake8-isort ; extra == 'linting'
Requires-Dist: flake8-quotes ; extra == 'linting'
Provides-Extra: testing
Requires-Dist: flask ; extra == 'testing'
Requires-Dist: pytest ; extra == 'testing'
Requires-Dist: pytest-cov ; extra == 'testing'
Requires-Dist: wheel ; extra == 'testing'
Requires-Dist: codecov ; extra == 'testing'
Requires-Dist: coverage ; extra == 'testing'
Requires-Dist: mock ; extra == 'testing'
Requires-Dist: faker ; extra == 'testing'
Requires-Dist: trustme ; extra == 'testing'
Requires-Dist: black ; extra == 'testing'
